[
  {
    "query": "melting face",
    "value": "Viral",
    "slug": "melting-face",
    "hasPage": false
  },
  {
    "query": "smiling face with tear",
    "value": "Viral",
    "slug": "smiling-face-with-tear",
    "hasPage": false
  },
  {
    "query": "skull",
    "value": "Viral",
    "slug": "skull",
    "hasPage": false
  },
  {
    "query": "rainbow flag",
    "value": "Seasonal",
    "slug": "rainbow-flag",
    "hasPage": false
  },
  {
    "query": "sun",
    "value": "Seasonal",
    "slug": "sun",
    "hasPage": false
  },
  {
    "query": "ice cream",
    "value": "Seasonal",
    "slug": "ice-cream",
    "hasPage": false
  },
  {
    "query": "watermelon",
    "value": "Seasonal",
    "slug": "watermelon",
    "hasPage": false
  },
  {
    "query": "graduation cap",
    "value": "Seasonal",
    "slug": "graduation-cap",
    "hasPage": false
  },
  {
    "query": "red heart",
    "value": "Evergreen",
    "slug": "red-heart",
    "hasPage": true
  },
  {
    "query": "face with tears of joy",
    "value": "Evergreen",
    "slug": "face-with-tears-of-joy",
    "hasPage": false
  },
  {
    "query": "thumbs up",
    "value": "Evergreen",
    "slug": "thumbs-up",
    "hasPage": false
  },
  {
    "query": "sparkles",
    "value": "High",
    "slug": "sparkles",
    "hasPage": false
  },
  {
    "query": "fire",
    "value": "High",
    "slug": "fire",
    "hasPage": false
  },
  {
    "query": "thinking face",
    "value": "Evergreen",
    "slug": "thinking-face",
    "hasPage": false
  },
  {
    "query": "partying face",
    "value": "High",
    "slug": "partying-face",
    "hasPage": true
  },
  {
    "query": "money bag",
    "value": "Evergreen",
    "slug": "money-bag",
    "hasPage": false
  },
  {
    "query": "eyes",
    "value": "High",
    "slug": "eyes",
    "hasPage": false
  },
  {
    "query": "pleading face",
    "value": "High",
    "slug": "pleading-face",
    "hasPage": false
  },
  {
    "query": "tropical drink",
    "value": "Seasonal",
    "slug": "tropical-drink",
    "hasPage": false
  },
  {
    "query": "handshake",
    "value": "High",
    "slug": "handshake",
    "hasPage": false
  }
]