{
  "name": "Grinning Face",
  "emoji": "😀",
  "slug": "grinning-face",
  "category": "Joy",
  "meaning": "The Grinning Face emoji represents happiness, cheerfulness, and a positive, upbeat emotional state. It is commonly used to express simple joy, friendliness, and good mood.",
  "unicode_name": "GRINNING FACE",
  "unicode_version": "Unicode 6.1",
  "codepoint": "U+1F600",
  "shortcodes": [":grinning:"],
  "usage_examples": [
    "I’m feeling really good today 😀",
    "That news made me smile 😀",
    "Hello everyone 😀"
  ],
  "chat_examples": [
    {
      "context": "Friendly greeting",
      "person_a": "Hey! How are you?",
      "person_b": "Doing great 😀"
    },
    {
      "context": "Positive reaction",
      "person_a": "We finally finished the project",
      "person_b": "That’s awesome 😀"
    },
    {
      "context": "Casual happiness",
      "person_a": "It’s such a nice day",
      "person_b": "It really is 😀"
    }
  ],
  "when_to_use": "Use this emoji when expressing happiness, friendliness, positive reactions, or a cheerful mood.",
  "when_not_to_use": "Avoid using it in serious, negative, or sensitive conversations where joy may feel inappropriate.",
  "related_emojis": [
    "smiling-face-with-smiling-eyes",
    "beaming-face-with-smiling-eyes",
    "smiling-face-with-sunglasses"
  ],
  "fun_fact": "😀 is one of the most commonly used emojis worldwide and is often considered the default symbol of happiness.",
  "faqs": [
    {
      "q": "What does the 😀 Grinning Face emoji mean?",
      "a": "It represents happiness, friendliness, and a cheerful mood."
    },
    {
      "q": "Is 😀 different from 😊?",
      "a": "Yes, 😀 is more open and expressive, while 😊 feels calmer and softer."
    },
    {
      "q": "Can 😀 be used professionally?",
      "a": "It may be used in informal or friendly work chats, but not in formal communication."
    },
    {
      "q": "Is 😀 always positive?",
      "a": "Yes, it generally conveys positivity and friendliness."
    },
    {
      "q": "Can 😀 be used as a greeting?",
      "a": "Yes, it is commonly used in friendly greetings."
    },
    {
      "q": "Does 😀 express excitement?",
      "a": "It expresses happiness but not intense excitement."
    },
    {
      "q": "Is 😀 suitable for social media?",
      "a": "Yes, it is widely used in captions and comments."
    },
    {
      "q": "Is 😀 universally recognized?",
      "a": "Yes, it is one of the most universally understood emojis."
    }
  ]
}
